{
    "rooms": {
        "1": {
            "booked": false,
            "capacity": 4,
            "equipment": [
                "bed",
                "air conditioner"
            ],
            "id": 1
        },
        "2": {
            "booked": false,
            "capacity": 2,
            "equipment": [
                "air conditioner"
            ],
            "id": 2
        },
        "4": {
            "booked": false,
            "capacity": 8,
            "equipment": [
                "air conditioner"
            ],
            "id": 4
        }
    },
    "rooms_id": 4
}
